layerx/__init__.py
layerx/datalake/__init__.py
layerx/datalake/annotation.py
layerx/datalake/constants.py
layerx/datalake/datalakeinterface.py
layerx/datalake/dataset.py
layerx/datalake/file_trash.py
layerx/datalake/file_upload.py
layerx/datalake/ground_truth.py
layerx/datalake/keys.py
layerx/datalake/label.py
layerx/datalake/logger.py
layerx/datalake/metadata.py
layerx/datalake/model_run.py
layerx/datalake/query.py
layerx/datalake/s3_interface.py
layerx/datalake/s3_upload.py
layerx/dataset/__init__.py
layerx/dataset/dataset.py
layerx/dataset/datasetinterface.py
layerx/dataset/logger.py
layerx/dataset/sync.py
layerx/studio/__init__.py
layerx/studio/logger.py
layerx/studio/project.py
layerx/studio/studiointerface.py
layerx_sdk-1.0.15.dist-info/METADATA
layerx_sdk-1.0.15.dist-info/WHEEL
layerx_sdk-1.0.15.dist-info/top_level.txt
layerx_sdk-1.0.15.dist-info/RECORD
